trix/__init__.py
trix/admin.py
trix/fields.py
trix/forms.py
trix/models.py
trix/urls.py
trix/utils.py
trix/views.py
trix/widgets.py
trix/static/trix/trix-core.js
trix/static/trix/trix-django.js
trix/static/trix/trix.css
trix/static/trix/trix.js
django_trix_fork-0.3.2.0.dist-info/LICENSE
django_trix_fork-0.3.2.0.dist-info/METADATA
django_trix_fork-0.3.2.0.dist-info/WHEEL
django_trix_fork-0.3.2.0.dist-info/top_level.txt
django_trix_fork-0.3.2.0.dist-info/RECORD
