Metadata-Version: 2.1
Name: django-trix-fork
Version: 0.3.2.0
Summary: Trix rich text editor widget for Django (Fork of https://github.com/tortillagroup/django-trix)
Home-page: https://github.com/adityatelange/django-trix-fork
Author: Jeremy Carbaugh, Aditya Telange
License: MIT
Platform: any
Classifier: Development Status :: 4 - Beta
Classifier: Environment :: Web Environment
Classifier: Framework :: Django
Classifier: Intended Audience :: Developers
Classifier: Operating System :: OS Independent
Classifier: Programming Language :: Python
Classifier: Programming Language :: Python :: 3.5
Classifier: Programming Language :: Python :: 3.6
Classifier: Topic :: Software Development :: Libraries :: Python Modules
